CHANGES.rst
MANIFEST.in
README.rst
bootstrap.py
buildout.cfg
setup.py
docs/LICENSE.rst
src/blog/__init__.py
src/blog.post.egg-info/PKG-INFO
src/blog.post.egg-info/SOURCES.txt
src/blog.post.egg-info/dependency_links.txt
src/blog.post.egg-info/entry_points.txt
src/blog.post.egg-info/namespace_packages.txt
src/blog.post.egg-info/not-zip-safe
src/blog.post.egg-info/pbr.json
src/blog.post.egg-info/requires.txt
src/blog.post.egg-info/top_level.txt
src/blog/post/__init__.py
src/blog/post/blog_post.py
src/blog/post/configure.zcml
src/blog/post/interfaces.py
src/blog/post/profile.py
src/blog/post/setuphandlers.py
src/blog/post/testing.py
src/blog/post/testing.zcml
src/blog/post/browser/__init__.py
src/blog/post/browser/blog_view.py
src/blog/post/browser/blogs_view.py
src/blog/post/browser/configure.zcml
src/blog/post/browser/logo.py
src/blog/post/browser/utils.py
src/blog/post/browser/static/.gitkeep
src/blog/post/browser/static/blogpost.png
src/blog/post/browser/static/comments.png
src/blog/post/browser/templates/blog_view.pt
src/blog/post/browser/templates/blogs_view.pt
src/blog/post/locales/blog.post.pot
src/blog/post/profiles/default/blog.post.txt
src/blog/post/profiles/default/browserlayer.xml
src/blog/post/profiles/default/metadata.xml
src/blog/post/profiles/default/types.xml
src/blog/post/profiles/default/types/Collection.xml
src/blog/post/profiles/default/types/Folder.xml
src/blog/post/profiles/default/types/blog_post.xml
src/blog/post/profiles/testing/blog.post-testing.txt
src/blog/post/profiles/testing/metadata.xml
src/blog/post/profiles/testing/properties.xml
src/blog/post/profiles/uninstall/browserlayer.xml
src/blog/post/tests/__init__.py
src/blog/post/tests/example.robot
src/blog/post/tests/test_example.py
src/blog/post/tests/test_robot.py