Metadata-Version: 1.1
Name: blog.post
Version: 0.1b3
Summary: This package is use to create a Plone blog site
Home-page: http://pypi.python.org/pypi/blog.post
Author: Benoît Suttor
Author-email: ben.suttor@gmail.com
License: GPL
Keywords: Plone Python
Platform: UNKNOWN
Classifier: Framework :: Plone
Classifier: Programming Language :: Python
